build/lib/legion-cicd/tools/tests.py
build/lib/legion-cicd/tools/update_version_files.py
build/lib/odahuflow/jupyterlab/__init__.py
build/lib/odahuflow/jupyterlab/api_state.py
build/lib/odahuflow/jupyterlab/extension.py
build/lib/odahuflow/jupyterlab/version.py
build/lib/odahuflow/jupyterlab/handlers/__init__.py
build/lib/odahuflow/jupyterlab/handlers/base.py
build/lib/odahuflow/jupyterlab/handlers/cloud.py
build/lib/odahuflow/jupyterlab/handlers/configuration.py
build/lib/odahuflow/jupyterlab/handlers/helper.py
build/lib/odahuflow/jupyterlab/handlers/oauth2.py
build/lib/odahuflow/jupyterlab/handlers/datamodels/__init__.py
build/lib/odahuflow/jupyterlab/handlers/datamodels/cloud.py
legion-cicd/tools/tests.py
legion-cicd/tools/update_version_files.py
odahu_flow_jupyterlab_plugin-1.6.1.data/data/README.md
odahuflow/jupyterlab/__init__.py
odahuflow/jupyterlab/api_state.py
odahuflow/jupyterlab/extension.py
odahuflow/jupyterlab/version.py
odahuflow/jupyterlab/handlers/__init__.py
odahuflow/jupyterlab/handlers/base.py
odahuflow/jupyterlab/handlers/cloud.py
odahuflow/jupyterlab/handlers/configuration.py
odahuflow/jupyterlab/handlers/helper.py
odahuflow/jupyterlab/handlers/oauth2.py
odahuflow/jupyterlab/handlers/datamodels/__init__.py
odahuflow/jupyterlab/handlers/datamodels/cloud.py
odahu_flow_jupyterlab_plugin-1.6.1.dist-info/LICENSE
odahu_flow_jupyterlab_plugin-1.6.1.dist-info/METADATA
odahu_flow_jupyterlab_plugin-1.6.1.dist-info/WHEEL
odahu_flow_jupyterlab_plugin-1.6.1.dist-info/top_level.txt
odahu_flow_jupyterlab_plugin-1.6.1.dist-info/RECORD
