Metadata-Version: 2.1
Name: odahu-flow-jupyterlab-plugin
Version: 1.6.1
Summary: A JupyterLab Notebook server extension for jupyter_odahuflow
Home-page: UNKNOWN
Author: Vlad Tokarev, Vitalik Solodilov
Author-email: vlad.tokarev.94@gmail.com, mcdkr@yandex.ru
License: Apache v2
Keywords: odahu-flow jupyterlab
Platform: UNKNOWN
Classifier: Programming Language :: Python :: 3.6
Classifier: Programming Language :: Python :: 3.7
Requires-Python: >=3.6
License-File: LICENSE
Requires-Dist: odahu-flow-sdk (==1.5.0rc6)
Requires-Dist: odahu-flow-cli (==1.5.0rc6)
Requires-Dist: notebook
Requires-Dist: pydantic (>=1.2)
Provides-Extra: testing
Requires-Dist: pylint (>=2.3.0) ; extra == 'testing'
Requires-Dist: jupyterlab (~=1.1) ; extra == 'testing'
